{
  "id": "city_cute_modular_small_building",
  "title": "Small Building",
  "label": "Small Building",
  "file": "city_cute_modular_small_building.json",
  "author": "Kenney",
  "description": "Loly-poly glb asset of Small Building.",
  "thumbnail": "",
  "url": "https://poly.pizza/",
  "artist_url": "https://poly.pizza",
  "tags": [
    "city",
    "cute",
    "modular"
  ],
  "model_url": "https://wumuyao1996.github.io/PhrollerDesigns/assets/models/files/city_cute_modular_small_building.glb"
}