{
  "id": "minimal-cartoon-rocketship-by-gambsmoore-dsjkFYy-rb0",
  "label": "Minimal Cartoon Rocketship",
  "file": "minimal-cartoon-rocketship-by-gambsmoore-dsjkFYy-rb0.json",
  "author": "Gambsmoore",
  "description": "Made this in 10 minutes as a joke for someone who wanted a rocket, but I quite like it, so here it is. \n\nCheck out other bad jokes: \n\nTwitter: https://twitter.com/gambsmoore\nYoutube: https://youtube.com/gambsmoore",
  "artist_url": "https://poly.pizza",
  "tags": [
    "peanuts",
    "shred",
    "skeleton"
  ],
  "model_url": "https://wumuyao1996.github.io/PhrollerDesigns/assets/models/files/minimal-cartoon-rocketship-by-gambsmoore-dsjkFYy-rb0.glb"
}