{
  "id": "stylized_collection_modular_platform",
  "title": "Platform",
  "label": "Platform",
  "file": "stylized_collection_modular_platform.json",
  "author": "MiniPoly",
  "description": "Loly-poly glb asset of Platform.",
  "thumbnail": "",
  "url": "https://poly.pizza/",
  "artist_url": "https://poly.pizza",
  "tags": [
    "stylized",
    "collection",
    "modular"
  ],
  "model_url": "https://wumuyao1996.github.io/PhrollerDesigns/assets/models/files/stylized_collection_modular_platform.glb"
}